{
    "AX": {
        "error": 0.015500256776417492, 
        "filter_outliers_dict": {
            "filter_outliers": true, 
            "iterations": 1, 
            "std_devs": 2
        }, 
        "fit": "Average", 
        "value": -0.14586073202876157
    }, 
    "H1": {
        "error": 0.01756929827327566, 
        "filter_outliers_dict": {
            "filter_outliers": true, 
            "iterations": 1, 
            "std_devs": 2
        }, 
        "fit": "Average", 
        "value": 0.04062940130865858
    }, 
    "H2": {
        "error": 0.012278497735359108, 
        "filter_outliers_dict": {
            "filter_outliers": true, 
            "iterations": 1, 
            "std_devs": 2
        }, 
        "fit": "Average", 
        "value": -0.08995406035806629
    }, 
    "L1": {
        "error": 0.014508781053214055, 
        "filter_outliers_dict": {
            "filter_outliers": true, 
            "iterations": 1, 
            "std_devs": 2
        }, 
        "fit": "Average", 
        "value": -0.03743537611978756
    }, 
    "L2(CDD)": {
        "error": 6.002781778695453e-23, 
        "filter_outliers_dict": {
            "filter_outliers": true, 
            "iterations": 1, 
            "std_devs": 2
        }, 
        "fit": "Average", 
        "value": -1.7936378757966893e-06
    }
}