{
    "Ar36": {
        "error": 0.0004006275038820664,
        "error_type": "",
        "fit": "previous",
        "references": [
            {
                "exclude": false,
                "record_id": "ba-01-H-100"
            }
        ],
        "value": 0.017453227995031753
    },
    "Ar37": {
        "error": 0.014144828043801119,
        "error_type": "",
        "fit": "previous",
        "references": [
            {
                "exclude": false,
                "record_id": "ba-01-H-100"
            }
        ],
        "value": 0.017643875839358683
    },
    "Ar38": {
        "error": 0.015263823866018966,
        "error_type": "",
        "fit": "previous",
        "references": [
            {
                "exclude": false,
                "record_id": "ba-01-H-100"
            }
        ],
        "value": 0.02188105964412565
    },
    "Ar39": {
        "error": 0.015743121474391872,
        "error_type": "",
        "fit": "previous",
        "references": [
            {
                "exclude": false,
                "record_id": "ba-01-H-100"
            }
        ],
        "value": 0.03716089046629742
    },
    "Ar40": {
        "error": 0.02197254877783562,
        "error_type": "",
        "fit": "previous",
        "references": [
            {
                "exclude": false,
                "record_id": "ba-01-H-100"
            }
        ],
        "value": 0.22931504981476605
    }
}