{
    "Ar36": {
        "error": 0.0007288489884857951, 
        "fit": "previous", 
        "references": [
            {
                "exclude": false, 
                "record_id": "ba-01-H-47"
            }
        ], 
        "value": 0.02985718660567777
    }, 
    "Ar37": {
        "error": 0.017719001646576117, 
        "fit": "previous", 
        "references": [
            {
                "exclude": false, 
                "record_id": "ba-01-H-47"
            }
        ], 
        "value": 0.030477772142810486
    }, 
    "Ar38": {
        "error": 0.02136069713838201, 
        "fit": "previous", 
        "references": [
            {
                "exclude": false, 
                "record_id": "ba-01-H-47"
            }
        ], 
        "value": 0.022948642173150263
    }, 
    "Ar39": {
        "error": 0.022838031803646297, 
        "fit": "previous", 
        "references": [
            {
                "exclude": false, 
                "record_id": "ba-01-H-47"
            }
        ], 
        "value": -0.006879869414051436
    }, 
    "Ar40": {
        "error": 0.03311480764592468, 
        "fit": "previous", 
        "references": [
            {
                "exclude": false, 
                "record_id": "ba-01-H-47"
            }
        ], 
        "value": 0.23549148224765287
    }
}